setup.py
ims_lti_py/__init__.py
ims_lti_py/launch_params.py
ims_lti_py/outcome_request.py
ims_lti_py/outcome_response.py
ims_lti_py/request_validator.py
ims_lti_py/tool_config.py
ims_lti_py/tool_consumer.py
ims_lti_py/tool_provider.py
ims_lti_py/utils.py
ims_lti_py.egg-info/PKG-INFO
ims_lti_py.egg-info/SOURCES.txt
ims_lti_py.egg-info/dependency_links.txt
ims_lti_py.egg-info/requires.txt
ims_lti_py.egg-info/top_level.txt
ims_lti_py.egg-info/zip-safe