Metadata-Version: 1.0
Name: ims-lti-py
Version: 0.5
Summary: A Python library to help implement IMS LTI tool consumers and providers
Home-page: https://github.com/tophatmonocle/ims_lti_py
Author: Anson MacKeracher
Author-email: anson@tophatmonocle.com
License: MIT License
Keywords: lti
Platform: UNKNOWN
